{
  "name": "cm3astralsorcrey:altar1",

  "disabled": false,

  "target-item": "astralsorcery:blockaltar",
  "target-count": 1,

  "duration": 200,
  "symmetrical": true,

  "catalyst": "astralsorcery:itemcraftingcomponent",

  "input-types": {
    "a": {
      "id": "astralsorcery:blockmarble",
      "meta": 3
    },
    "b": {
      "id": "thaumcraft:slab_greatwood",
      "meta": 8,
      "item": {
        "id": "thaumcraft:slab_greatwood",
        "meta": 0,
        "count": 8
      }
    },
    "c": {
      "id": "thaumcraft:slab_greatwood",
      "meta": 0
    },
    "d": {
      "id": "astralsorcery:blockblackmarble",
      "meta": 0
    },
    "e": {
      "id": "thaumcraft:plank_greatwood",
      "meta": 0
    }
  },
  "shape": [
    [
      [
        "a",
        "a",
        "a"
      ],
      [
        "a",
        "d",
        "a"
      ],
      [
        "a",
        "a",
        "a"
      ]
    ],
    [
      [
        "b",
        "b",
        "b"
      ],
      [
        "b",
        "e",
        "b"
      ],
      [
        "b",
        "b",
        "b"
      ]
    ],
    [
      [
        "c",
        "c",
        "c"
      ],
      [
        "c",
        "e",
        "c"
      ],
      [
        "c",
        "c",
        "c"
      ]
    ]
  ]
}